deep_confusables/__init__.py
deep_confusables/domains.py
deep_confusables/main.py
deep_confusables/utils/__init__.py
deep_confusables/utils/files.py
deep_confusables/utils/images.py
deep_confusables/utils/printing.py
deep_confusables/utils/similarity.py
deep_confusables/utils/unicode.py
deepconfusables/__init__.py
deepconfusables/domains.py
deepconfusables/main.py
deepconfusables/utils/__init__.py
deepconfusables/utils/files.py
deepconfusables/utils/images.py
deepconfusables/utils/printing.py
deepconfusables/utils/similarity.py
deepconfusables/utils/unicode.py
deep_confusables-1.1.1.dist-info/LICENSE.md
deep_confusables-1.1.1.dist-info/METADATA
deep_confusables-1.1.1.dist-info/WHEEL
deep_confusables-1.1.1.dist-info/entry_points.txt
deep_confusables-1.1.1.dist-info/top_level.txt
deep_confusables-1.1.1.dist-info/RECORD
