Metadata-Version: 2.1
Name: deep-confusables
Version: 1.1.1
Summary: deep-confusables - cli generates new variations of an input based on similarity matrix generated by deep-confusables-similarity.
Home-page: https://github.com/next-security-lab/deep-confusables-cli
Author: José Ignacion Escribano & Miguel Hernández & Alfonso Muñoz
Author-email: deep.confusables@gmail.com
License: MIT
Platform: UNKNOWN
Classifier: Environment :: Console
Classifier: Intended Audience :: System Administrators
Classifier: Intended Audience :: Other Audience
Classifier: License :: OSI Approved :: BSD License
Classifier: Operating System :: MacOS
Classifier: Operating System :: Microsoft :: Windows
Classifier: Operating System :: POSIX
Classifier: Programming Language :: Python :: 3
Requires-Python: >3.5.0
Requires-Dist: tqdm
Requires-Dist: colorama
Requires-Dist: python-whois
Requires-Dist: requests
Requires-Dist: virustotal-api
Provides-Extra: dev
Requires-Dist: flake8 ; extra == 'dev'
